{
    "_comment": "zamiast uzywac bazy danych uzyje pliku json",
    "users": [
        {
            "username": "testUser",
            "password": "Test1234",
            "email": "test@mail.pl"
        },
        {
            "usernameS": "pawel",
            "passwordS": "Pawel123",
            "emailS": "pawel@mail.pl"
        },
        {
            "usernameS": "Tadam",
            "passwordS": "Tadam123",
            "emailS": "Tadam@mail.pl"
        },
        {
            "usernameS": "Tadam",
            "passwordS": "Tadam123",
            "emailS": "Tadam@mail.pl"
        },
        {
            "usernameS": "Tadam",
            "passwordS": "Tadam123",
            "emailS": "Tadam@mail.pl"
        },
        {
            "usernameS": "Tadam",
            "passwordS": "Tadam123",
            "emailS": "Tadam@mail.pl"
        },
        {
            "usernameS": "Tadam",
            "passwordS": "Tadam123",
            "emailS": "Tadam@mail.pl"
        },
        {
            "username": "Tadam",
            "password": "Tadam123",
            "email": "Tadam@mail.pl"
        },
        {
            "username": "testUse",
            "password": "Test123",
            "email": "test@t.pl"
        },
        {
            "username": "testUser2",
            "password": "Test1234",
            "email": "testuser2@mail.pl"
        }
    ]
}